main.py
zahlen-0.0.1.dist-info/METADATA
zahlen-0.0.1.dist-info/WHEEL
zahlen-0.0.1.dist-info/top_level.txt
zahlen-0.0.1.dist-info/RECORD
