Metadata-Version: 2.4
Name: zahlen
Version: 0.0.1
Summary: Number Theory Package
Requires-Python: >=3.13
